pyefd.py
pyefd-1.6.0.dist-info/LICENSE
pyefd-1.6.0.dist-info/METADATA
pyefd-1.6.0.dist-info/WHEEL
pyefd-1.6.0.dist-info/top_level.txt
pyefd-1.6.0.dist-info/RECORD
