Metadata-Version: 2.1
Name: pyefd
Version: 1.6.0
Summary: Python implementation of "Elliptic Fourier Features of a Closed Contour"
Home-page: UNKNOWN
Author: Henrik Blidh
Author-email: henrik.blidh@nedomkull.com
License: MIT
Keywords: elliptic fourier descriptors,fourier descriptors,shape descriptors,image analysis
Platform: UNKNOWN
Classifier: Development Status :: 5 - Production/Stable
Classifier: Operating System :: OS Independent
Classifier: Intended Audience :: Science/Research
Classifier: Intended Audience :: Developers
Classifier: License :: OSI Approved :: MIT License
Classifier: Topic :: Software Development
Classifier: Topic :: Scientific/Engineering
Classifier: Programming Language :: Python :: 2
Classifier: Programming Language :: Python :: 2.7
Classifier: Programming Language :: Python :: 3
Classifier: Programming Language :: Python :: 3.4
Classifier: Programming Language :: Python :: 3.5
Classifier: Programming Language :: Python :: 3.6
Classifier: Programming Language :: Python :: Implementation :: CPython
Classifier: Programming Language :: Python :: Implementation :: PyPy
Requires-Python: >=2.7.10
License-File: LICENSE
